traducteur/context/__init__.py
traducteur/context/base.py
traducteur/context/mongo.py
traducteur/context/sqlite.py
traducteur/exceptions/tasks/__init__.py
traducteur/exceptions/tasks/base.py
traducteur/exceptions/tasks/worker.py
traducteur/managers/__init__.py
traducteur/managers/base.py
traducteur/managers/filters/base.py
traducteur/managers/filters/types/__init__.py
traducteur/managers/filters/types/base.py
traducteur/managers/filters/types/boolean_filter.py
traducteur/managers/filters/types/datetime_filter.py
traducteur/managers/filters/types/exists_filter.py
traducteur/managers/filters/types/number_filter.py
traducteur/managers/filters/types/string_filter.py
traducteur/managers/mongo.py
traducteur/managers/query/__init__.py
traducteur/managers/query/sql.py
traducteur/managers/sql.py
traducteur/models/base/__init__.py
traducteur/models/base/base.py
traducteur/models/base/database.py
traducteur/models/document/mongo.py
traducteur/models/document/redis.py
traducteur/models/relational/sql.py
traducteur/tasks/base/__init__.py
traducteur/tasks/base/base.py
traducteur/tasks/base/lifetime.py
traducteur/tasks/base/status.py
traducteur/tasks/task/__init__.py
traducteur/tasks/task/redis.py
traducteur/tasks/worker/base.py
traducteur/tasks/worker/redis.py
traducteur-0.4.7.dist-info/LICENSE
traducteur-0.4.7.dist-info/METADATA
traducteur-0.4.7.dist-info/WHEEL
traducteur-0.4.7.dist-info/RECORD
