Metadata-Version: 2.1
Name: traducteur
Version: 0.4.7
Summary: Traducteur is the middle man to handle your basic data needs.
Author: Seppe De Langhe
Author-email: seppedelanghe@gmail.com
Requires-Python: >=3.8,<4.0
Classifier: Programming Language :: Python :: 3
Classifier: Programming Language :: Python :: 3.8
Classifier: Programming Language :: Python :: 3.9
Classifier: Programming Language :: Python :: 3.10
Classifier: Programming Language :: Python :: 3.11
Provides-Extra: all
Provides-Extra: caching
Provides-Extra: mongo
Provides-Extra: nosql
Provides-Extra: sql
Provides-Extra: tasks
Requires-Dist: dill (>=0.3.6,<0.4.0) ; extra == "tasks" or extra == "all"
Requires-Dist: pydantic (>=1.10.4,<2.0.0)
Requires-Dist: pymongo (>=4.3.3,<5.0.0) ; extra == "mongo" or extra == "nosql" or extra == "all"
Requires-Dist: redis (>=4.2.2,<5.0.0) ; extra == "tasks" or extra == "caching" or extra == "nosql" or extra == "all"
Requires-Dist: sqlalchemy (>=1.4.46,<2.0.0) ; extra == "sql" or extra == "all"
